iso/.iso
iso/__init__.py
iso/__main__.py
iso/exc.py
iso/feature.py
iso/iso.py
iso/learn.py
iso/models.py
iso/transform.py
iso-0.1.0.dist-info/LICENSE
iso-0.1.0.dist-info/METADATA
iso-0.1.0.dist-info/WHEEL
iso-0.1.0.dist-info/entry_points.txt
iso-0.1.0.dist-info/top_level.txt
iso-0.1.0.dist-info/RECORD
