Metadata-Version: 2.1
Name: iso
Version: 0.1.0
Summary: Modular data transformations for machine learning workflows.
Home-page: https://github.com/bprinty/iso
Author: Blake Printy
Author-email: bprinty@gmail.com
License: MIT
Keywords: iso,machine-learning,learning,data,modelling,ai
Platform: UNKNOWN
Classifier: Intended Audience :: Developers
Classifier: License :: OSI Approved :: MIT License
Classifier: Natural Language :: English
Classifier: Programming Language :: Python :: 2
Classifier: Programming Language :: Python :: 2.6
Classifier: Programming Language :: Python :: 2.7
Classifier: Programming Language :: Python :: 3
Classifier: Programming Language :: Python :: 3.3
Classifier: Programming Language :: Python :: 3.4
Requires-Dist: numpy (>=1.9.1)
Requires-Dist: cached-property (>=1.2.0)
Requires-Dist: gems (>=0.2.1)
Requires-Dist: joblib (>=0.7.1)
Requires-Dist: scipy (>=0.15.1)
Requires-Dist: scikit-learn (>=0.18.1)
Requires-Dist: pandas (>=0.16.0)
Requires-Dist: PyYAML (>=5.1.2)
Requires-Dist: future (>=0.16.0)
